{
  "sha256": "34f51d5e304ebb9eb2e943d23fb305aae0349e79cdda2be0311b075edfb4749c",
  "braco": "B2",
  "modelo": "gemma3:12b",
  "scenario_id": "T-CLT-02-001",
  "run_id": 2,
  "seed": 137,
  "timestamp_iso": "2026-04-28T13:07:18Z",
  "prompt_sha": "54fed52f1361028c4b39bac92f25e2dfe4146042ea59002edc5741c8f1792790",
  "response_text": "## Análise Jurídico-Trabalhista do Caso Banco de Horas em Call Center\n\nCom base no contexto normativo fornecido, apresento a análise, decisão recomendada e fundamentação jurídica do caso.\n\n**1. ANÁLISE: Dispositivos Normativos Aplicáveis**\n\nO cenário apresentado envolve a implementação unilateral de um banco de horas em uma empresa de call center, sem negociação sindical e com a assinatura de empregados por meio de memorando interno. A questão central é a validade desse sistema, considerando a ausência de acordo ou convenção coletiva que o autorize.\n\nAnalisando o contexto, identificamos a seguinte limitação: **não há dispositivos normativos explícitos** (leis, acordos, convenções, etc.) fornecidos que tratem especificamente do tema do banco de horas ou da validade de memorandos de adesão.  Portanto, a análise deve se basear nos princípios gerais do Direito do Trabalho e na interpretação que se faz da legislação trabalhista em casos semelhantes.\n\n**2. DECISÃO RECOMENDADA**\n\nRecomenda-se que a implementação do banco de horas, nas condições descritas, seja considerada **nula e inválida**. A empresa deverá ser notificada para cessar a prática e regularizar a situação dos empregados, compensando as horas extras não pagas durante o período em que o banco de horas esteve em vigor.\n\n**3. FUNDAMENTAÇÃO NORMATIVA**\n\nEmbora o contexto não forneça dispositivos normativos específicos, a decisão acima se fundamenta nos princípios gerais do Direito do Trabalho e na interpretação que se faz da legislação em casos semelhantes.  A ausência de um acordo ou convenção coletiva que autorize o banco de horas é um ponto crucial.\n\n*   **Princípio da Primazia do Negociado:** O Direito do Trabalho brasileiro adota o princípio da primazia do negociado, ou seja, os acordos e convenções coletivas de trabalho (ACTs e CCTs) têm prevalência sobre a lei em matérias regulamentadas por ela (art. 8º, IV, da Constituição Federal). A ausência de um ACT ou CCT que autorize o banco de horas demonstra que a empresa agiu em desacordo com esse princípio.\n\n*   **Necessidade de Negociação Coletiva:** A implementação de um banco de horas, por envolver a possibilidade de prorrogação da jornada de trabalho e a compensação posterior, é considerada uma alteração contratual. Alterações contratuais como essa, em regra, exigem negociação coletiva para serem válidas (Súmula 266 do TST: \"A validade de acordo ou contrato individual de trabalho, que se desvia do contrato coletivo, depende da prévia e efetiva negociação coletiva\").\n\n*   **Atipicidade da Adesão Individual:** A assinatura de um memorando interno pelos empregados, mesmo que com o objetivo de aderir ao banco de horas, não convalida a implementação unilateral. A assinatura individual, nesse contexto, não representa uma negociação livre e informada, mas sim uma adesão forçada, em prejuízo dos direitos dos trabalhadores.\n\n*   **Limitação Temporal da Empresa:** A alegação da empresa de que os acordos individuais seriam válidos para um período de até 6 meses não encontra respaldo legal, especialmente na ausência de um ACT ou CCT que estabeleça essa limitação. A lei não estabelece um prazo máximo para a validade de um banco de horas, e a imposição de um limite unilateral pela empresa é abusiva.\n\n*   **Acúmulo Excessivo:** O acúmulo de até 120 horas no período de 9 meses é um indicativo de que o sistema de banco de horas está sendo utilizado de forma desproporcional, em prejuízo do descanso e da saúde dos empregados.\n\n**Limitação da Análise:**\n\nÉ importante reiterar que a análise acima é limitada pelo contexto normativo fornecido. Uma análise completa exigiria a consulta à legislação trabalhista em geral, à jurisprudência dos tribunais do trabalho e a outros documentos relevantes, como acordos e convenções coletivas da categoria.\n",
  "tokens_in": 265,
  "tokens_out": 892,
  "latency_ms": 49718,
  "status": "ok",
  "error": null,
  "clingo_active_sovereign": [],
  "clingo_active_elastic": [],
  "clingo_satisfiability": ""
}