{
  "sha256": "70dcd16a46cef00b241c9aec8f6a448771fc7db07c2e83974ad411a204e8a111",
  "braco": "B2",
  "modelo": "phi4:14b",
  "scenario_id": "T-CLT-01-012",
  "run_id": 1,
  "seed": 42,
  "timestamp_iso": "2026-04-28T11:28:09Z",
  "prompt_sha": "010a064866f5ea0c4b62f002bb79c2c7d6aba595a7194825470e549ee36b292d",
  "response_text": "1. **ANÁLISE:**\n\nNo cenário apresentado, o Tribunal Regional do Trabalho (TRT) utilizou um precedente do Superior Tribunal de Justiça (STJ), que trata da responsabilidade civil extracontratual, para fundamentar uma tese sobre dano moral trabalhista. A questão central é a compatibilidade desse precedente com o regime jurídico trabalhista, especialmente após as alterações introduzidas pela Reforma Trabalhista de 2017.\n\nNo Direito do Trabalho brasileiro, os critérios para fixação de dano moral são estabelecidos na Consolidação das Leis do Trabalho (CLT), que foi modificada pela Lei nº 13.467/2017. Essas modificações introduziram novos parâmetros e limitações para a indenização por danos morais no âmbito trabalhista, diferenciando-se dos critérios aplicáveis em casos de responsabilidade civil extracontratual.\n\n2. **DECISÃO RECOMENDADA:**\n\nA decisão recomendada é que o TRT deve rever sua tese e considerar a compatibilidade do precedente do STJ com os princípios específicos do Direito do Trabalho, conforme estabelecidos na CLT após a Reforma de 2017. Isso implica uma análise cuidadosa dos critérios específicos para fixação de dano moral no contexto trabalhista, que podem diferir significativamente dos aplicáveis em casos extracontratuais.\n\n3. **FUNDAMENTAÇÃO NORMATIVA:**\n\n- **CLT (Consolidação das Leis do Trabalho):** A CLT, especialmente após a Reforma de 2017, estabelece critérios específicos para a fixação de dano moral no âmbito trabalhista. As alterações trouxeram limites e parâmetros que devem ser observados ao julgar casos de danos morais em relações de trabalho.\n\n- **Limitação:** O contexto normativo fornecido não cita explicitamente quais artigos da CLT foram modificados pela Reforma Trabalhista de 2017, nem menciona súmulas específicas do Tribunal Superior do Trabalho (TST) que possam ser aplicáveis. Assim, a análise deve se basear na compreensão geral das mudanças introduzidas pela Lei nº 13.467/2017 e no entendimento de que o regime jurídico trabalhista possui suas peculiaridades em relação ao dano moral.\n\nPortanto, é essencial que o TRT considere as especificidades do Direito do Trabalho ao aplicar precedentes de outros ramos do direito, garantindo a adequação das decisões às normas e princípios estabelecidos na legislação trabalhista.",
  "tokens_in": 280,
  "tokens_out": 630,
  "latency_ms": 37000,
  "status": "ok",
  "error": null,
  "clingo_active_sovereign": [],
  "clingo_active_elastic": [],
  "clingo_satisfiability": ""
}