{
  "sha256": "935c60a79c5dc7d1a496f61bc1bf53d15b0be15f5dc114d3ebac5314467edd54",
  "braco": "B1",
  "modelo": "llama3.1:8b",
  "scenario_id": "T-CLT-04-002",
  "run_id": 1,
  "seed": 42,
  "timestamp_iso": "2026-04-28T07:02:41Z",
  "prompt_sha": "c3729bae48ca01abd6c07208ac7dde170ba2d481ce181e1573f1aa588bdd7ad6",
  "response_text": "**ANÁLISE**\n\n1. **Identificação dos dispositivos legais aplicáveis**: A questão em debate envolve o adicional noturno, previsto no artigo 73 da CLT (Lei nº 5.889/1973). O regime de revezamento é mencionado, que se refere ao regime de trabalho onde os empregados trabalham períodos alternados de dia e noite.\n\n2. **Interpretação no caso concreto**: A Súmula TST 60 (adicional noturno — regime de revezamento) é aplicável quando o regime de trabalho do empregado envolve revezamento entre turnos, incluindo períodos noturnos. Nesse contexto, a interpretação da CLT e a jurisprudência do TST indicam que o adicional noturno deve ser pago quando o empregado trabalha em período noturno, mesmo se esse período for fixo.\n\n**DECISÃO RECOMENDADA**\n\nA decisão recomendada é que o empregador pague o adicional noturno ao empregado, pois seu regime de trabalho envolve revezamento e períodos noturnos fixos, enquadrando-se na hipótese da Súmula TST 60.\n\n**FUNDAMENTAÇÃO NORMATIVA**\n\n- **Artigo 73 da CLT**: Regulamenta o adicional noturno, estabelecendo que será pago aos empregados que trabalham em período noturno.\n\n- **Súmula TST 60 (adicional noturno — regime de revezamento)**: Estabelece que o adicional noturno é devido quando o regime de trabalho envolve revezamento, incluindo períodos noturnos. Essa súmula é fundamental para a interpretação do caso concreto.\n\n- **Precedentes constitucionais e jurisprudência**: Embora não mencionados explicitamente na questão, a fundamentação se baseia em precedentes que estabelecem a proteção ao trabalho noturno como uma condição mais favorável para os empregados, contribuindo para a qualidade de vida.\n\nEm resumo, a decisão recomendada é que o adicional noturno seja pago ao empregado, com base na aplicação da Súmula TST 60 e na interpretação do artigo 73 da CLT.",
  "tokens_in": 333,
  "tokens_out": 529,
  "latency_ms": 18328,
  "status": "ok",
  "error": null,
  "clingo_active_sovereign": [],
  "clingo_active_elastic": [],
  "clingo_satisfiability": ""
}