{
  "sha256": "b93ecf06df2e7e5a5c7cf06699a4743daddc587158c9c9283d9841cb2bfc1afd",
  "braco": "B1",
  "modelo": "gemma3:12b",
  "scenario_id": "T-CLT-01-008",
  "run_id": 2,
  "seed": 137,
  "timestamp_iso": "2026-04-28T03:40:15Z",
  "prompt_sha": "65ae71bdbd6a5957a903048be7849ac95f7c43a5d8cf96b88aa3d1dce5a8a617",
  "response_text": "## Análise Jurídico-Trabalhista: Condenação por Horas de Sobreaviso com Base em OJ Cancelada\n\n**1. ANÁLISE**\n\nO cenário apresentado revela uma situação jurídica problemática, onde um Acórdão do Tribunal Regional do Trabalho (TRT) fundamenta sua decisão de condenação por horas de sobreaviso em uma Orientação Jurisprudencial (OJ) da SDI-1 do TST (OJ 394) que foi, subsequentemente, cancelada e incorporada à Súmula 428, com alterações significativas em seu conteúdo.\n\n**Dispositivos Legais Aplicáveis e Interpretação:**\n\n* **CLT, Art. 58:** Este artigo estabelece a possibilidade de compensação financeira pelas horas de sobreaviso, quando o empregado é colocado à disposição do empregador para ser acionado em caso de necessidade, mesmo fora do horário normal de trabalho. A lei não define o valor da compensação, deixando espaço para negociação coletiva ou, na ausência desta, para a fixação judicial.\n* **CLT, Art. 59:**  Regulamenta a compensação das horas de sobreaviso, estabelecendo que, se o empregado for acionado durante o período de sobreaviso, as horas trabalhadas devem ser remuneradas como extras.\n* **TST, OJ 394 (Revogada):**  Originalmente, a OJ 394 da SDI-1 do TST, antes de sua revogação, estabelecia que o simples fato de o empregado ser colocado à disposição do empregador em regime de sobreaviso gera direito à percepção de horas extras, mesmo que não seja acionado. Essa interpretação era bastante favorável ao trabalhador.\n* **TST, Súmula 428:**  Após a revogação da OJ 394, o TST incorporou seus elementos à Súmula 428, que, em sua redação atual, estabelece que \"O tempo de sobreaviso deve ser remunerado como hora extraordinária, apenas quando o empregado for acionado para prestar serviços\".  A Súmula 428, portanto, restringe o direito à compensação, exigindo a efetiva prestação de serviços durante o período de sobreaviso.\n* **Princípio da Segurança Jurídica:** A aplicação de normas revogadas viola o princípio da segurança jurídica, que exige que as decisões judiciais sejam baseadas em normas vigentes e aplicáveis ao caso concreto.\n\n**Interpretação no Caso Concreto:**\n\nA decisão do TRT, ao se basear na OJ 394, incorre em erro de fundamentação. A OJ 394 não está mais em vigor, tendo sido substituída pela Súmula 428, que possui interpretação mais restritiva sobre o direito às horas de sobreaviso. A aplicação da OJ 394, portanto, contraria a jurisprudência atual do TST e a evolução do entendimento sobre a matéria.  A condenação baseada em uma OJ revogada compromete a segurança jurídica e a previsibilidade das decisões judiciais.\n\n**2. DECISÃO RECOMENDADA**\n\nRecomenda-se a **reforma do Acórdão do TRT**. A decisão deve ser anulada ou, alternativamente, reformada para que a condenação por horas de sobreaviso seja recalculada com base na Súmula 428 do TST, considerando apenas as horas efetivamente trabalhadas durante o período de sobreaviso.\n\n**3. FUNDAMENTAÇÃO NORMATIVA**\n\n* **CLT, Art. 58 e 59:**  Fundamentam a possibilidade de compensação ou remuneração de horas de sobreaviso, mas deixam espaço para a definição do alcance dessa compensação.\n* **TST, Súmula 428:**  É a orientação jurisprudencial atual do TST sobre o tema, estabelecendo que o tempo de sobreaviso deve ser remunerado como hora extraordinária apenas quando o empregado for acionado para prestar serviços.  A Súmula 428, portanto, é a norma aplicável ao caso concreto.\n* **TST, OJ 394 (Revogada):**  Embora tenha sido utilizada como fundamento pela decisão do TRT, a OJ 394 não possui validade jurídica, tendo sido expressamente revogada e incorporada à Súmula 428 com conteúdo distinto.\n* **Princípio da Legalidade e Segurança Jurídica:** A aplicação de uma norma revogada viola o princípio da legalidade e compromete a segurança jurídica, que exige que as decisões judiciais sejam fundamentadas em normas vigentes e aplicáveis. A jurisprudência do TST tem reiteradamente enfatizado a importância de se observar a vigência das normas utilizadas como fundamento para as decisões judiciais.\n* **Precedentes do TST:**  Diversos julgados do TST têm reforçado a importância de se observar a vigência das Orientações Jurisprudenciais e Súmulas, evitando a aplicação de normas revogadas ou superadas.  A aplicação de normas revogadas pode gerar decisões conflitantes e insegurança jurídica.\n\n**Observações Adicionais:**\n\n* É importante ressaltar que a análise do caso concreto deve considerar a existência de negociação coletiva que possa tratar do tema das horas de sobreaviso. Caso haja acordo ou convenção coletiva que estabeleça regras diferentes, estas devem prevalecer sobre a interpretação da Súmula 428.\n* A decisão do TRT deve ser fundamentada de forma clara e objetiva, explicando o motivo da reforma do Acórdão e a aplicação da Súmula 428 ao caso concreto.\n\n\n\nEsta análise e recomendação visam garantir a correta aplicação do Direito do Trabalho brasileiro, observando a jurisprudência atual do TST e os princípios da legalidade e segurança jurídica.",
  "tokens_in": 266,
  "tokens_out": 1285,
  "latency_ms": 69889,
  "status": "ok",
  "error": null,
  "clingo_active_sovereign": [],
  "clingo_active_elastic": [],
  "clingo_satisfiability": ""
}