{
  "sha256": "c1ba60f13f2eac5cb77fab03789e1645c92c98ace4fa878f8d00d9038fa2f2ce",
  "braco": "B2",
  "modelo": "gemma3:12b",
  "scenario_id": "T-CLT-02-001",
  "run_id": 3,
  "seed": 271,
  "timestamp_iso": "2026-04-28T13:08:06Z",
  "prompt_sha": "54fed52f1361028c4b39bac92f25e2dfe4146042ea59002edc5741c8f1792790",
  "response_text": "## Análise Jurídico-Trabalhista do Caso Banco de Horas em Call Center\n\nCom base no contexto normativo fornecido, apresento a análise, decisão recomendada e fundamentação jurídica do caso.\n\n**1. ANÁLISE: Dispositivos Normativos Aplicáveis**\n\nO cenário apresentado envolve a implementação unilateral de um banco de horas em uma empresa de call center, sem negociação sindical, e a alegação da empresa de que acordos individuais seriam válidos apenas para um período de até 6 meses.  Analisando o contexto, os seguintes pontos merecem destaque:\n\n*   **Ausência de Negociação Sindical:** O texto informa que \"o sindicato da categoria não celebrou qualquer ACT ou CCT autorizando o banco de horas.\" Isso é crucial, pois a implementação de banco de horas, em regra, exige negociação coletiva.\n*   **Acordos Individuais:** A empresa alega a validade de acordos individuais assinados pelos empregados, limitando o período de acumulação a 6 meses. A validade desses acordos é questionável, especialmente considerando a ausência de negociação coletiva.\n*   **Limite de Acumulação:** O texto indica que os empregados acumularam até 120 horas em um período de 9 meses. A validade desse limite, e a alegação da empresa de que o período de 6 meses seria o limite válido, dependem da análise da legalidade da implementação do banco de horas.\n\n**2. DECISÃO RECOMENDADA**\n\nRecomenda-se a **invalidade da implementação unilateral do banco de horas** e a **anulação dos acordos individuais** que o regulamentam, especialmente no que tange ao limite de acumulação de 120 horas em 9 meses.  A empresa deverá, em caráter de urgência, suspender a prática e buscar a negociação com o sindicato da categoria para regularizar a situação.\n\n**3. FUNDAMENTAÇÃO NORMATIVA**\n\nEmbora o contexto não forneça textos normativos específicos (como a Constituição Federal, CLT ou Súmulas do TST), a informação crucial é a **ausência de Autorização Coletiva de Trabalho (ACT) ou Convenção Coletiva de Trabalho (CCT)** que autorize o banco de horas.\n\n*   **Princípio da Negociação Coletiva:** A implementação de banco de horas, como forma de compensação de horas extras, é uma questão que envolve condições de trabalho e, portanto, deve ser objeto de negociação coletiva entre empregadores e empregados, conforme o que se entende ser a interpretação mais razoável do princípio da negociação coletiva. A imposição unilateral, sem essa negociação, viola esse princípio.\n*   **Acordos Individuais e a Negociação Coletiva:** Acordos individuais não podem contrariar a lei ou a negociação coletiva. No caso, a assinatura de um memorando pelos empregados não substitui a necessidade de negociação coletiva para a implementação do banco de horas. Mesmo que os empregados tenham assinado, a validade do acordo é questionável, pois a matéria é de interesse coletivo e exige a participação do sindicato.\n*   **Limite de Acumulação:** A alegação da empresa de que o limite de 6 meses seria válido, em face dos acordos individuais, é improcedente, uma vez que a validade desses acordos é duvidosa devido à ausência de negociação coletiva.  O contexto não estabelece um limite máximo de horas a serem acumuladas, mas a acumulação de 120 horas em 9 meses pode ser considerada excessiva, dependendo da natureza do trabalho e da possibilidade de compensação.\n\n**Limitação do Contexto:**\n\nÉ importante ressaltar que a análise é limitada ao contexto normativo fornecido. Uma análise completa exigiria a consulta à legislação trabalhista vigente (CLT, Constituição Federal, etc.), jurisprudência do Tribunal Superior do Trabalho (TST) e outras normas aplicáveis ao caso. A ausência desses elementos no contexto impede uma avaliação mais aprofundada e precisa.\n",
  "tokens_in": 265,
  "tokens_out": 884,
  "latency_ms": 48280,
  "status": "ok",
  "error": null,
  "clingo_active_sovereign": [],
  "clingo_active_elastic": [],
  "clingo_satisfiability": ""
}